ant_colony/__init__.py
ant_colony/ant.py
ant_colony/ant_colony.py
ant_colony/graph.py
ant_colony-0.1.2.dist-info/DESCRIPTION.rst
ant_colony-0.1.2.dist-info/METADATA
ant_colony-0.1.2.dist-info/RECORD
ant_colony-0.1.2.dist-info/WHEEL
ant_colony-0.1.2.dist-info/metadata.json
ant_colony-0.1.2.dist-info/top_level.txt
