Metadata-Version: 1.0
Name: ant_colony
Version: 0.1.2
Summary: Implementation of the Ant Colony system
Home-page: https://github.com/jurekpawlikowski/ant-colony
Author: Jerzy Pawlikowski
Author-email: me@jerzypawlikowski.pl
License: The MIT License (MIT)
